inc_map/__main__.py
inc_map/front.py
inc_map/readable_path.py
inc_map/back/project.py
inc_map/back/common_features/abstract_inclusion_inspector.py
inc_map/back/common_features/abstract_inclusion_instruction.py
inc_map/back/support_c/include_inspector.py
inc_map/back/support_c/include_matcher.py
inc_map/back/support_python/import_inspector.py
inc_map/back/support_python/import_matcher.py
inc_map/back/support_python/source_code_reader.py
InclusionMap-1.5.2.dist-info/LICENSE
InclusionMap-1.5.2.dist-info/METADATA
InclusionMap-1.5.2.dist-info/WHEEL
InclusionMap-1.5.2.dist-info/entry_points.txt
InclusionMap-1.5.2.dist-info/top_level.txt
InclusionMap-1.5.2.dist-info/RECORD
